data_anonymization/__init__.py
data_anonymization/api.py
data_anonymization/firebase-key.json
data_anonymization-0.1.0.dist-info/METADATA
data_anonymization-0.1.0.dist-info/WHEEL
data_anonymization-0.1.0.dist-info/entry_points.txt
data_anonymization-0.1.0.dist-info/top_level.txt
data_anonymization-0.1.0.dist-info/RECORD
